azure/mgmt/workloadssapvirtualinstance/__init__.py
azure/mgmt/workloadssapvirtualinstance/_client.py
azure/mgmt/workloadssapvirtualinstance/_configuration.py
azure/mgmt/workloadssapvirtualinstance/_model_base.py
azure/mgmt/workloadssapvirtualinstance/_patch.py
azure/mgmt/workloadssapvirtualinstance/_serialization.py
azure/mgmt/workloadssapvirtualinstance/_version.py
azure/mgmt/workloadssapvirtualinstance/py.typed
azure/mgmt/workloadssapvirtualinstance/aio/__init__.py
azure/mgmt/workloadssapvirtualinstance/aio/_client.py
azure/mgmt/workloadssapvirtualinstance/aio/_configuration.py
azure/mgmt/workloadssapvirtualinstance/aio/_patch.py
azure/mgmt/workloadssapvirtualinstance/aio/operations/__init__.py
azure/mgmt/workloadssapvirtualinstance/aio/operations/_operations.py
azure/mgmt/workloadssapvirtualinstance/aio/operations/_patch.py
azure/mgmt/workloadssapvirtualinstance/models/__init__.py
azure/mgmt/workloadssapvirtualinstance/models/_enums.py
azure/mgmt/workloadssapvirtualinstance/models/_models.py
azure/mgmt/workloadssapvirtualinstance/models/_patch.py
azure/mgmt/workloadssapvirtualinstance/operations/__init__.py
azure/mgmt/workloadssapvirtualinstance/operations/_operations.py
azure/mgmt/workloadssapvirtualinstance/operations/_patch.py
azure_mgmt_workloadssapvirtualinstance-1.0.0.dist-info/LICENSE
azure_mgmt_workloadssapvirtualinstance-1.0.0.dist-info/METADATA
azure_mgmt_workloadssapvirtualinstance-1.0.0.dist-info/WHEEL
azure_mgmt_workloadssapvirtualinstance-1.0.0.dist-info/top_level.txt
azure_mgmt_workloadssapvirtualinstance-1.0.0.dist-info/RECORD
